{
 "sections": [
  {
   "id": "83cef6d6-638b-f11e-d644-ed4207d9e41b",
   "title": "Page 1",
   "files": [],
   "path": [],
   "type": "markdown",
   "content-file": ".guides/content/Page-1-83ce.md",
   "chapter": false,
   "reset": [],
   "teacherOnly": false,
   "closeTerminalSession": true,
   "learningObjectives": ""
  },
  {
   "id": "d672dab6-17e1-c0c9-1d11-72b8f269c455",
   "title": "Page 2",
   "files": [],
   "path": [],
   "type": "markdown",
   "content-file": ".guides/content/Page-2-d672.md",
   "chapter": false,
   "reset": [],
   "teacherOnly": false,
   "closeTerminalSession": true,
   "learningObjectives": ""
  }
 ],
 "theme": "light",
 "scripts": [],
 "lexikonTopic": "",
 "useSubmitButtons": true,
 "useMarkAsComplete": true
}